api_to_case/__init__.py
api_to_case/api2case.py
api_to_case/main.py
api_to_case/common/__init__.py
api_to_case/common/tools.py
api2case-0.1.22.dist-info/METADATA
api2case-0.1.22.dist-info/WHEEL
api2case-0.1.22.dist-info/entry_points.txt
api2case-0.1.22.dist-info/top_level.txt
api2case-0.1.22.dist-info/zip-safe
api2case-0.1.22.dist-info/RECORD
